pyspark_utils/__init__.py
pyspark_utils/helper.py
pyspark_utils/op.py
pyspark_utils-1.8.0.dist-info/DESCRIPTION.rst
pyspark_utils-1.8.0.dist-info/METADATA
pyspark_utils-1.8.0.dist-info/RECORD
pyspark_utils-1.8.0.dist-info/WHEEL
pyspark_utils-1.8.0.dist-info/metadata.json
pyspark_utils-1.8.0.dist-info/top_level.txt
