Metadata-Version: 2.0
Name: pyspark-utils
Version: 1.8.0
Summary: The missing PySpark utils
Home-page: https://github.com/xiaoxq/pyspark-utils
Author: Xiangquan Xiao
Author-email: xiaoxiangquan@gmail.com
License: Apache License Version 2.0
Platform: UNKNOWN
Classifier: Programming Language :: Python
Classifier: License :: OSI Approved :: Apache Software License
Classifier: Operating System :: OS Independent
Requires-Dist: absl-py
